<?xml version="1.0" encoding="UTF-8"?>
<objects serializationModel="Studio.02.02.00">
	<object class="AudioFile" id="{55889add-59e5-4490-8475-f97ff9e362bb}">
		<property name="assetPath">
			<value>GroundWalking_4.mp3</value>
		</property>
		<property name="frequencyInKHz">
			<value>48</value>
		</property>
		<property name="channelCount">
			<value>2</value>
		</property>
		<property name="length">
			<value>0.504</value>
		</property>
		<relationship name="masterAssetFolder">
			<destination>{c53e70ba-b042-42b3-920b-482171776b1b}</destination>
		</relationship>
	</object>
</objects>
